super_resolution/__init__.py
super_resolution/__version__.py
super_resolution/entry_points.py
super_resolution/super_resolution.py
super_resolution-0.2.4.dist-info/METADATA
super_resolution-0.2.4.dist-info/WHEEL
super_resolution-0.2.4.dist-info/entry_points.txt
super_resolution-0.2.4.dist-info/top_level.txt
super_resolution-0.2.4.dist-info/RECORD
